{
  "gameId": "11077",
  "date": "2017-10-25",
  "divId": 174,
  "seasonName": "Winter 2017",
  "mode": "regular",
  "home": {
    "teamId": "1112",
    "name": "Blackhawks"
  },
  "away": {
    "teamId": "1109",
    "name": "Kings"
  },
  "scoring": {
    "home": {
      "p1": 1,
      "p2": 0,
      "p3": 3,
      "ot": 0,
      "final": 4
    },
    "away": {
      "p1": 2,
      "p2": 1,
      "p3": 0,
      "ot": 0,
      "final": 3
    }
  },
  "goals": [
    {
      "period": "1",
      "time": "00:02:16",
      "team": {
        "teamId": "1109",
        "name": "Kings"
      },
      "scorer": "#82 - Caleb  Sohl",
      "assist1": null,
      "assist2": null
    },
    {
      "period": "1",
      "time": "00:04:39",
      "team": {
        "teamId": "1109",
        "name": "Kings"
      },
      "scorer": "#55 - Chris  Yoko",
      "assist1": "#7 - Mike  Hoard",
      "assist2": null
    },
    {
      "period": "1",
      "time": "00:08:22",
      "team": {
        "teamId": "1112",
        "name": "Blackhawks"
      },
      "scorer": "#8 - Brendan  Millice",
      "assist1": "#25 - Jamie  Prime",
      "assist2": "#7 - Tyler  Kniaz"
    },
    {
      "period": "2",
      "time": "00:00:15",
      "team": {
        "teamId": "1109",
        "name": "Kings"
      },
      "scorer": "#26 - Erik  Hovland",
      "assist1": null,
      "assist2": null
    },
    {
      "period": "3",
      "time": "00:00:49",
      "team": {
        "teamId": "1112",
        "name": "Blackhawks"
      },
      "scorer": "#8 - Brendan  Millice",
      "assist1": "#32 - Simon  Flom",
      "assist2": "#27 - David  McAndrews"
    },
    {
      "period": "3",
      "time": "00:02:04",
      "team": {
        "teamId": "1112",
        "name": "Blackhawks"
      },
      "scorer": "#32 - Simon  Flom",
      "assist1": null,
      "assist2": null
    },
    {
      "period": "3",
      "time": "00:05:46",
      "team": {
        "teamId": "1112",
        "name": "Blackhawks"
      },
      "scorer": "#7 - Tyler  Kniaz",
      "assist1": "#25 - Jamie  Prime",
      "assist2": null
    }
  ],
  "penalties": [
    {
      "period": "3",
      "time": "00:04:07",
      "team": {
        "teamId": "1112",
        "name": "Blackhawks"
      },
      "player": "#24 - Scott  Kuehn",
      "pim": 2,
      "offense": "trip",
      "isMajor": false,
      "isMatch": false
    },
    {
      "period": "3",
      "time": "00:10:45",
      "team": {
        "teamId": "1112",
        "name": "Blackhawks"
      },
      "player": "#27 - David  McAndrews",
      "pim": 2,
      "offense": "trip",
      "isMajor": false,
      "isMatch": false
    }
  ],
  "_updated": "2026-06-06T19:22:21.243Z"
}