{
  "gameId": "12519",
  "date": "2019-03-27",
  "divId": 194,
  "seasonName": "Winter 2018",
  "mode": "regular",
  "home": {
    "teamId": "1232",
    "name": "Swarm"
  },
  "away": {
    "teamId": "1230",
    "name": "Goons"
  },
  "scoring": {
    "home": {
      "p1": 2,
      "p2": 1,
      "p3": 1,
      "ot": 0,
      "final": 4
    },
    "away": {
      "p1": 1,
      "p2": 3,
      "p3": 2,
      "ot": 0,
      "final": 6
    }
  },
  "goals": [
    {
      "period": "1",
      "time": "00:08:42",
      "team": {
        "teamId": "1232",
        "name": "Swarm"
      },
      "scorer": "#92 - Matt  Frazza",
      "assist1": "#51 - Tyler  Kniaz",
      "assist2": null
    },
    {
      "period": "1",
      "time": "00:12:06",
      "team": {
        "teamId": "1232",
        "name": "Swarm"
      },
      "scorer": "#51 - Tyler  Kniaz",
      "assist1": "#92 - Matt  Frazza",
      "assist2": null
    },
    {
      "period": "1",
      "time": "00:14:11",
      "team": {
        "teamId": "1230",
        "name": "Goons"
      },
      "scorer": "#82 - Neil  Schoenthaler",
      "assist1": "#9 - Brian  Mehnert",
      "assist2": null
    },
    {
      "period": "2",
      "time": "00:00:01",
      "team": {
        "teamId": "1230",
        "name": "Goons"
      },
      "scorer": "#24 - Tom  Spiewak",
      "assist1": null,
      "assist2": null
    },
    {
      "period": "2",
      "time": "00:07:04",
      "team": {
        "teamId": "1230",
        "name": "Goons"
      },
      "scorer": "#82 - Neil  Schoenthaler",
      "assist1": "#9 - Brian  Mehnert",
      "assist2": null
    },
    {
      "period": "2",
      "time": "00:09:04",
      "team": {
        "teamId": "1230",
        "name": "Goons"
      },
      "scorer": "#82 - Neil  Schoenthaler",
      "assist1": "#9 - Brian  Mehnert",
      "assist2": "#7 - John  Dagley"
    },
    {
      "period": "2",
      "time": "00:13:12",
      "team": {
        "teamId": "1232",
        "name": "Swarm"
      },
      "scorer": "#8 - Brenden  Millice",
      "assist1": "#51 - Tyler  Kniaz",
      "assist2": null
    },
    {
      "period": "3",
      "time": "00:01:07",
      "team": {
        "teamId": "1232",
        "name": "Swarm"
      },
      "scorer": "#92 - Matt  Frazza",
      "assist1": "#51 - Tyler  Kniaz",
      "assist2": "#8 - Brenden  Millice"
    },
    {
      "period": "3",
      "time": "00:06:58",
      "team": {
        "teamId": "1230",
        "name": "Goons"
      },
      "scorer": "#82 - Neil  Schoenthaler",
      "assist1": "#19 - Joe  Dunn",
      "assist2": "#7 - John  Dagley"
    },
    {
      "period": "3",
      "time": "00:13:55",
      "team": {
        "teamId": "1230",
        "name": "Goons"
      },
      "scorer": "#19 - Joe  Dunn",
      "assist1": "#82 - Neil  Schoenthaler",
      "assist2": "#7 - John  Dagley"
    }
  ],
  "penalties": [
    {
      "period": "2",
      "time": "00:14:21",
      "team": {
        "teamId": "1230",
        "name": "Goons"
      },
      "player": "#25 - Malcolm  Hyson",
      "pim": 2,
      "offense": "slash",
      "isMajor": false,
      "isMatch": false
    },
    {
      "period": "3",
      "time": "00:03:23",
      "team": {
        "teamId": "1230",
        "name": "Goons"
      },
      "player": "#38 - Eric  Mastromatteo",
      "pim": 2,
      "offense": "trip",
      "isMajor": false,
      "isMatch": false
    },
    {
      "period": "3",
      "time": "00:06:14",
      "team": {
        "teamId": "1230",
        "name": "Goons"
      },
      "player": "#38 - Eric  Mastromatteo",
      "pim": 2,
      "offense": "hold",
      "isMajor": false,
      "isMatch": false
    },
    {
      "period": "3",
      "time": "00:07:53",
      "team": {
        "teamId": "1230",
        "name": "Goons"
      },
      "player": "#11 - Kevin  Powers",
      "pim": 2,
      "offense": "hold",
      "isMajor": false,
      "isMatch": false
    }
  ],
  "_updated": "2026-06-06T19:48:10.048Z"
}