{
  "gameId": "14602",
  "date": "2022-01-30",
  "divId": 242,
  "seasonName": "Winter 2021",
  "mode": "regular",
  "home": {
    "teamId": "1498",
    "name": "Avalanche"
  },
  "away": {
    "teamId": "1495",
    "name": "Punishers"
  },
  "scoring": {
    "home": {
      "p1": 0,
      "p2": 0,
      "p3": 3,
      "ot": 0,
      "final": 3
    },
    "away": {
      "p1": 1,
      "p2": 2,
      "p3": 3,
      "ot": 0,
      "final": 6
    }
  },
  "goals": [
    {
      "period": "1",
      "time": "00:08:50",
      "team": {
        "teamId": "1495",
        "name": "Punishers"
      },
      "scorer": "#16 - Patrick  Smith",
      "assist1": "#21 - Mike  Hawthorne",
      "assist2": "#15 - Phil  Wind"
    },
    {
      "period": "2",
      "time": "00:06:58",
      "team": {
        "teamId": "1495",
        "name": "Punishers"
      },
      "scorer": "#1 - Matt  ODriscoll",
      "assist1": "#37 - Nick  Desport",
      "assist2": null
    },
    {
      "period": "2",
      "time": "00:13:11",
      "team": {
        "teamId": "1495",
        "name": "Punishers"
      },
      "scorer": "#16 - Patrick  Smith",
      "assist1": null,
      "assist2": null
    },
    {
      "period": "3",
      "time": "00:02:19",
      "team": {
        "teamId": "1495",
        "name": "Punishers"
      },
      "scorer": "#27 - Dave  Lin",
      "assist1": "#21 - Mike  Hawthorne",
      "assist2": "#16 - Patrick  Smith"
    },
    {
      "period": "3",
      "time": "00:05:00",
      "team": {
        "teamId": "1498",
        "name": "Avalanche"
      },
      "scorer": "#33 - Steven  Terenzlo",
      "assist1": null,
      "assist2": null
    },
    {
      "period": "3",
      "time": "00:09:19",
      "team": {
        "teamId": "1495",
        "name": "Punishers"
      },
      "scorer": "#21 - Mike  Hawthorne",
      "assist1": "#12 - Dave  OMalley",
      "assist2": "#16 - Patrick  Smith"
    },
    {
      "period": "3",
      "time": "00:10:05",
      "team": {
        "teamId": "1495",
        "name": "Punishers"
      },
      "scorer": "#27 - Dave  Lin",
      "assist1": null,
      "assist2": null
    },
    {
      "period": "3",
      "time": "00:10:52",
      "team": {
        "teamId": "1498",
        "name": "Avalanche"
      },
      "scorer": "#10 - Kevin  Free",
      "assist1": null,
      "assist2": null
    },
    {
      "period": "3",
      "time": "00:13:28",
      "team": {
        "teamId": "1498",
        "name": "Avalanche"
      },
      "scorer": "#33 - Steven  Terenzlo",
      "assist1": "#10 - Kevin  Free",
      "assist2": null
    }
  ],
  "penalties": [
    {
      "period": "1",
      "time": "00:01:15",
      "team": {
        "teamId": "1495",
        "name": "Punishers"
      },
      "player": "#15 - Phil  Wind",
      "pim": 2,
      "offense": "check",
      "isMajor": false,
      "isMatch": false
    },
    {
      "period": "2",
      "time": "00:09:10",
      "team": {
        "teamId": "1495",
        "name": "Punishers"
      },
      "player": "#42 - Ryan  ODriscoll",
      "pim": 2,
      "offense": "rough",
      "isMajor": false,
      "isMatch": false
    },
    {
      "period": "2",
      "time": "00:12:36",
      "team": {
        "teamId": "1498",
        "name": "Avalanche"
      },
      "player": "#33 - Steven  Terenzlo",
      "pim": 2,
      "offense": "delay",
      "isMajor": false,
      "isMatch": false
    },
    {
      "period": "3",
      "time": "00:01:30",
      "team": {
        "teamId": "1495",
        "name": "Punishers"
      },
      "player": "#1 - Matt  ODriscoll",
      "pim": 2,
      "offense": "high stick",
      "isMajor": false,
      "isMatch": false
    },
    {
      "period": "3",
      "time": "00:01:38",
      "team": {
        "teamId": "1498",
        "name": "Avalanche"
      },
      "player": "#33 - Steven  Terenzlo",
      "pim": 2,
      "offense": "hook",
      "isMajor": false,
      "isMatch": false
    },
    {
      "period": "3",
      "time": "00:01:38",
      "team": {
        "teamId": "1495",
        "name": "Punishers"
      },
      "player": "#21 - Mike  Hawthorne",
      "pim": 2,
      "offense": "rough",
      "isMajor": false,
      "isMatch": false
    }
  ],
  "_updated": "2026-06-06T20:31:35.109Z"
}