{
  "gameId": "15273",
  "date": "2022-09-17",
  "divId": 254,
  "seasonName": "Summer 2022",
  "mode": "regular",
  "home": {
    "teamId": "1570",
    "name": "Grey Goons"
  },
  "away": {
    "teamId": "1568",
    "name": "Coyotes"
  },
  "scoring": {
    "home": {
      "p1": 6,
      "p2": 3,
      "p3": 1,
      "ot": 0,
      "final": 10
    },
    "away": {
      "p1": 0,
      "p2": 0,
      "p3": 0,
      "ot": 0,
      "final": 0
    }
  },
  "goals": [
    {
      "period": "1",
      "time": "00:02:36",
      "team": {
        "teamId": "1570",
        "name": "Grey Goons"
      },
      "scorer": "#49 - Greg  Mullen",
      "assist1": "#76 - Mike  Floyd",
      "assist2": null
    },
    {
      "period": "1",
      "time": "00:03:19",
      "team": {
        "teamId": "1570",
        "name": "Grey Goons"
      },
      "scorer": "#11 - Dave  Brown",
      "assist1": "#44 - Mick  Ellsworth",
      "assist2": null
    },
    {
      "period": "1",
      "time": "00:04:55",
      "team": {
        "teamId": "1570",
        "name": "Grey Goons"
      },
      "scorer": "#28 - Alex  Henry",
      "assist1": "#19 - Joe  Dunn",
      "assist2": "#49 - Greg  Mullen"
    },
    {
      "period": "1",
      "time": "00:06:55",
      "team": {
        "teamId": "1570",
        "name": "Grey Goons"
      },
      "scorer": "#76 - Mike  Floyd",
      "assist1": "#44 - Mick  Ellsworth",
      "assist2": null
    },
    {
      "period": "1",
      "time": "00:11:18",
      "team": {
        "teamId": "1570",
        "name": "Grey Goons"
      },
      "scorer": "#49 - Greg  Mullen",
      "assist1": "#54 - Jerry  Gibbons",
      "assist2": null
    },
    {
      "period": "1",
      "time": "00:13:42",
      "team": {
        "teamId": "1570",
        "name": "Grey Goons"
      },
      "scorer": "#11 - Dave  Brown",
      "assist1": "#44 - Mick  Ellsworth",
      "assist2": null
    },
    {
      "period": "2",
      "time": "00:00:55",
      "team": {
        "teamId": "1570",
        "name": "Grey Goons"
      },
      "scorer": "#19 - Joe  Dunn",
      "assist1": null,
      "assist2": null
    },
    {
      "period": "2",
      "time": "00:11:07",
      "team": {
        "teamId": "1570",
        "name": "Grey Goons"
      },
      "scorer": "#12 - Paul  Zalocha",
      "assist1": "#49 - Greg  Mullen",
      "assist2": null
    },
    {
      "period": "2",
      "time": "00:11:46",
      "team": {
        "teamId": "1570",
        "name": "Grey Goons"
      },
      "scorer": "#49 - Greg  Mullen",
      "assist1": "#28 - Alex  Henry",
      "assist2": null
    },
    {
      "period": "3",
      "time": "00:06:52",
      "team": {
        "teamId": "1570",
        "name": "Grey Goons"
      },
      "scorer": "#19 - Joe  Dunn",
      "assist1": null,
      "assist2": null
    }
  ],
  "penalties": [
    {
      "period": "1",
      "time": "00:08:04",
      "team": {
        "teamId": "1568",
        "name": "Coyotes"
      },
      "player": "#5 - Andy  Loggia",
      "pim": 2,
      "offense": "hook",
      "isMajor": false,
      "isMatch": false
    },
    {
      "period": "2",
      "time": "00:07:45",
      "team": {
        "teamId": "1570",
        "name": "Grey Goons"
      },
      "player": "#100 - Goalie  Substitute",
      "pim": 2,
      "offense": "trip",
      "isMajor": false,
      "isMatch": false
    }
  ],
  "_updated": "2026-06-06T20:46:48.704Z"
}