{
  "gameId": "15823",
  "date": "2023-01-28",
  "divId": 265,
  "seasonName": "Winter 2022",
  "mode": "regular",
  "home": {
    "teamId": "1633",
    "name": "Blue Dogs"
  },
  "away": {
    "teamId": "1631",
    "name": "Thunder"
  },
  "scoring": {
    "home": {
      "p1": 4,
      "p2": 0,
      "p3": 0,
      "ot": 0,
      "final": 4
    },
    "away": {
      "p1": 2,
      "p2": 1,
      "p3": 0,
      "ot": 0,
      "final": 3
    }
  },
  "goals": [
    {
      "period": "1",
      "time": "00:00:46",
      "team": {
        "teamId": "1631",
        "name": "Thunder"
      },
      "scorer": "#11 - Mark  Boyd",
      "assist1": "#22 - Michael  Huston",
      "assist2": "#21 - Brendan  Williams"
    },
    {
      "period": "1",
      "time": "00:02:37",
      "team": {
        "teamId": "1633",
        "name": "Blue Dogs"
      },
      "scorer": "#16 - Sue  Felter",
      "assist1": "#33 - Brandon  Boling",
      "assist2": null
    },
    {
      "period": "1",
      "time": "00:08:58",
      "team": {
        "teamId": "1633",
        "name": "Blue Dogs"
      },
      "scorer": "#11 - Cindy  Huber",
      "assist1": "#22 - Amir  Tahami",
      "assist2": "#25 - Neil  Dsouza"
    },
    {
      "period": "1",
      "time": "00:10:02",
      "team": {
        "teamId": "1631",
        "name": "Thunder"
      },
      "scorer": "#21 - Brendan  Williams",
      "assist1": "#98 - Conor  McGrath",
      "assist2": null
    },
    {
      "period": "1",
      "time": "00:13:50",
      "team": {
        "teamId": "1633",
        "name": "Blue Dogs"
      },
      "scorer": "#11 - Cindy  Huber",
      "assist1": "#25 - Neil  Dsouza",
      "assist2": "#22 - Amir  Tahami"
    },
    {
      "period": "1",
      "time": "00:15:33",
      "team": {
        "teamId": "1633",
        "name": "Blue Dogs"
      },
      "scorer": "#8 - Reid  Maki",
      "assist1": "#33 - Brandon  Boling",
      "assist2": null
    },
    {
      "period": "2",
      "time": "00:00:43",
      "team": {
        "teamId": "1631",
        "name": "Thunder"
      },
      "scorer": "#22 - Michael  Huston",
      "assist1": "#11 - Mark  Boyd",
      "assist2": null
    }
  ],
  "penalties": [
    {
      "period": "1",
      "time": "00:11:18",
      "team": {
        "teamId": "1633",
        "name": "Blue Dogs"
      },
      "player": "#100 - Goalie  Substitue",
      "pim": 2,
      "offense": "too many",
      "isMajor": false,
      "isMatch": false
    },
    {
      "period": "3",
      "time": "00:04:14",
      "team": {
        "teamId": "1633",
        "name": "Blue Dogs"
      },
      "player": "#47 - David  Hitchock",
      "pim": 2,
      "offense": "rough",
      "isMajor": false,
      "isMatch": false
    }
  ],
  "_updated": "2026-06-06T20:59:39.201Z"
}