{
  "gameId": "16256",
  "date": "2023-09-24",
  "divId": 270,
  "seasonName": "Summer 2023",
  "mode": "regular",
  "home": {
    "teamId": "1665",
    "name": "Toronto"
  },
  "away": {
    "teamId": "1668",
    "name": "Red Dragons"
  },
  "scoring": {
    "home": {
      "p1": 3,
      "p2": 2,
      "p3": 1,
      "ot": 0,
      "final": 6
    },
    "away": {
      "p1": 1,
      "p2": 0,
      "p3": 0,
      "ot": 0,
      "final": 1
    }
  },
  "goals": [
    {
      "period": "1",
      "time": "00:01:24",
      "team": {
        "teamId": "1665",
        "name": "Toronto"
      },
      "scorer": "#23 - Trevor  Blair",
      "assist1": null,
      "assist2": null
    },
    {
      "period": "1",
      "time": "00:02:13",
      "team": {
        "teamId": "1665",
        "name": "Toronto"
      },
      "scorer": "#44 - Jim  McGovern",
      "assist1": null,
      "assist2": null
    },
    {
      "period": "1",
      "time": "00:06:35",
      "team": {
        "teamId": "1665",
        "name": "Toronto"
      },
      "scorer": "#92 - Maddy  Padgett",
      "assist1": null,
      "assist2": null
    },
    {
      "period": "1",
      "time": "00:08:51",
      "team": {
        "teamId": "1668",
        "name": "Red Dragons"
      },
      "scorer": "#18 - Zac  Shoewalter",
      "assist1": "#21 - Brandon  Jones",
      "assist2": null
    },
    {
      "period": "2",
      "time": "00:10:12",
      "team": {
        "teamId": "1665",
        "name": "Toronto"
      },
      "scorer": "#44 - Jim  McGovern",
      "assist1": null,
      "assist2": null
    },
    {
      "period": "2",
      "time": "00:14:24",
      "team": {
        "teamId": "1665",
        "name": "Toronto"
      },
      "scorer": "#92 - Maddy  Padgett",
      "assist1": null,
      "assist2": null
    },
    {
      "period": "3",
      "time": "00:03:35",
      "team": {
        "teamId": "1665",
        "name": "Toronto"
      },
      "scorer": "#92 - Maddy  Padgett",
      "assist1": "#18 - Russ  Smith",
      "assist2": null
    }
  ],
  "penalties": [
    {
      "period": "1",
      "time": "00:05:27",
      "team": {
        "teamId": "1665",
        "name": "Toronto"
      },
      "player": "#48 - Randy  Sasai",
      "pim": 2,
      "offense": "hook",
      "isMajor": false,
      "isMatch": false
    }
  ],
  "_updated": "2026-06-06T21:05:43.492Z"
}