{
  "gameId": "18901",
  "date": "2026-04-24",
  "divId": 321,
  "seasonName": "Winter 2025",
  "mode": "regular",
  "home": {
    "teamId": "1970",
    "name": "Outlaws"
  },
  "away": {
    "teamId": "1968",
    "name": "British Bulldogs"
  },
  "scoring": {
    "home": {
      "p1": 1,
      "p2": 1,
      "p3": 0,
      "ot": 0,
      "final": 2
    },
    "away": {
      "p1": 1,
      "p2": 0,
      "p3": 0,
      "ot": 0,
      "final": 1
    }
  },
  "goals": [
    {
      "period": "1",
      "time": "00:11:07",
      "team": {
        "teamId": "1968",
        "name": "British Bulldogs"
      },
      "scorer": "#2 - Ari  Loggia",
      "assist1": "#82 - Justin  MacDonald",
      "assist2": null
    },
    {
      "period": "1",
      "time": "00:14:41",
      "team": {
        "teamId": "1970",
        "name": "Outlaws"
      },
      "scorer": "#41 - Tony  Gorney",
      "assist1": null,
      "assist2": null
    },
    {
      "period": "2",
      "time": "00:06:03",
      "team": {
        "teamId": "1970",
        "name": "Outlaws"
      },
      "scorer": "#77 - Ryan  OConnell",
      "assist1": null,
      "assist2": null
    }
  ],
  "penalties": [
    {
      "period": "2",
      "time": "00:00:13",
      "team": {
        "teamId": "1968",
        "name": "British Bulldogs"
      },
      "player": "#28 - Carrick  Randall",
      "pim": 2,
      "offense": "rough",
      "isMajor": false,
      "isMatch": false
    },
    {
      "period": "2",
      "time": "00:05:07",
      "team": {
        "teamId": "1970",
        "name": "Outlaws"
      },
      "player": "#31 - Kevin  Loughery",
      "pim": 2,
      "offense": "trip",
      "isMajor": false,
      "isMatch": false
    },
    {
      "period": "2",
      "time": "00:12:36",
      "team": {
        "teamId": "1968",
        "name": "British Bulldogs"
      },
      "player": "#28 - Carrick  Randall",
      "pim": 2,
      "offense": "int",
      "isMajor": false,
      "isMatch": false
    },
    {
      "period": "3",
      "time": "00:07:20",
      "team": {
        "teamId": "1968",
        "name": "British Bulldogs"
      },
      "player": "#44 - Scott  Kuehn",
      "pim": 2,
      "offense": "rough",
      "isMajor": false,
      "isMatch": false
    }
  ],
  "_updated": "2026-06-06T18:38:41.565Z"
}